xia_diff_match_patch/__init__.py
xia_diff_match_patch/diff.py
xia_diff_match_patch-0.0.3.dist-info/LICENSE.txt
xia_diff_match_patch-0.0.3.dist-info/METADATA
xia_diff_match_patch-0.0.3.dist-info/WHEEL
xia_diff_match_patch-0.0.3.dist-info/top_level.txt
xia_diff_match_patch-0.0.3.dist-info/RECORD
