Metadata-Version: 2.1
Name: xia-diff-match-patch
Version: 0.0.3
Summary: UNKNOWN
Home-page: https://develop.x-i-a.com/docs/xia-diff-match-patch/0.0.3/index.html
Author: Neil Fraser
Author-email: fraser@google.com
License: UNKNOWN
Platform: UNKNOWN
Requires-Python: >=3.9
License-File: LICENSE.txt
